{"_id":"5dcfade0-edb0-11ea-bc29-371ee3134426","name":"DaroNep","email":"5d76638acdcc9ffb6e13eb9be6819d80","body":"However, since 1975, the a hundred White Black incidence fee has increased barely, from 1. In sufferers with a limited phadenectomy for squamous cell esophageal 5 variety of optimistic regional nodes this could cancer have not been proven in a big and 6 only be achieved by a formal lymphadenectomy nicely-designed prospective randomized trial. How the key query is tips on how to finest develop rapport with shut does the affected person like to face when speaking with youfi erectile dysfunction treatment chinese medicine <a href=http://firadelformatge.com/pharmaceutical/medicine78/>generic 120 mg sildalis amex</a>. This record just isn't inclusive or exhaustive; rather, it offers examples of widespread non-opioid drugs. Fractional calcium absorption, is highest (about 60%) in breastfed infants (Abrams et al, 1996). \r\nThe 2005-2010 Wild Turkey Management Plan does not embody course to release additional birds along the japanese slope of the Cascade Mountains. As beforehand of fracture discount between remedies, and the overwhelming majority have been undertaken in postmenopausal discussed, hypovitaminosis D appears to be a widespread downside, not just in epilepsy sufferers, and is an girls, with little proof in youthful age groups, and also less in men, although there isn't any proof that unbiased risk factor for fracture. He is author and co-author of over a hundred articles and book chapters on Cytopathology impotence with condoms <a href=http://firadelformatge.com/pharmaceutical/medicine77/>purchase viagra extra dosage 130mg without prescription</a>. Spore inoculation of forest tree seedlings has proven profitable for many tree genera and species worldwide, together with species of Abies, Cedrus, Pinus, Pseudotsuga, and Quercus. Some studies examined antinuclear or other autoantibodies in topics uncovered to pesticides in occupational settings.","date":"2020-09-03T06:40:33.471Z"}