{"_id":"7f1dc730-f80e-11ea-8403-95ec720fc278","name":"Rufuspiofs","email":"bbc51168ea8507f2fbf1b91a5e035ebe","body":"The dynamic forces of getting older and/or changing into adult, having romantic relationships, transferring out of and additional away from treatment, managing changing info and recommendation about the level of risk to fertility, having peers changing into parents and so on needed to be managed within their personal and social context in which most cancers and fertility associated issues competed with other forces. He smokes one pack of cigarettes per day and has done so since he was 15 years old. Mention of commerce names or commercial merchandise does not constitute enlevels at 10 wks time-point, but signifcantly decreased at 24 wks in arsenic/ dorsement or recommendations for use <a href=https://www.lifemedical.us/clinical-approach/article681/> symptoms 9 days after ovulation generic lamotrigine 200mg without prescription</a>. \r\nThe question of employment is essential when considering the needs of people with epilepsy. Supraventricular arrhythmias following an acute alcoholic binge, sometimes related to holiday events or long weekends. The impact of country of origin could be explained by genetic elements or by totally different environmental exposures and dwelling situations in the different countries <a href=https://www.lifemedical.us/clinical-approach/article677/> muscle relaxers to treat addiction generic mefenamic 500 mg without prescription</a>. Measuring oral parison of the impact of edoxaban, a direct factor Xa inhibitor, with direct inhibitors of thrombin and factor Xa: a recommendaa direct thrombin inhibitor, melagatran, and heparin on intraceretion from the Subcommittee on Control of Anticoagulation of bral hemorrhage induced by collagenase in rats. Although extraordinarily nodular lesions, nevertheless, the use of these imaging modalities rare, renal endometriosis ought to be included within the vary is especially indicated in the presence of pulmonary symptoms. Estimating the danger of future reading difficulties in kindergarten youngsters: A analysis-based mostly mannequin and its medical implementation <a href=https://www.lifemedical.us/clinical-approach/article680/> asthma high altitude order montelukast 5 mg with visa</a>. In studies where one arm did not include some type of sedation, or 220 used a lower level of sedation, peri-procedural pain was considerably greater, though this didn't appear to have any impact on overall patient preferences. Jabs and Jolts syndrome sensitivity, which are situated throughout the area of trigemi(пїЅa number of jabs,пїЅ пїЅice-pick acheпїЅ). In the preliminary regimen, it is necessary to make use of antibiotics infections per a thousand days in danger <a href=https://www.lifemedical.us/clinical-approach/article678/> medicine yoga purchase on line phenytoin</a>. Patients should be evaluated for the warning indicators of pancreatitis and inspired to seek remedy if they occur. A sling psychrometer is one the most effective tools for measuring relпїЅ ative humidity, and is comparatively cheap. In addition, many stories have revealed that Judges at the city level are unfamiliar with the law and typically use their very own private interpretation of Sharia Law <a href=https://www.lifemedical.us/clinical-approach/article683/> antimicrobial light cheap cefdinir uk</a>. \r\nThere is 6пїЅ7 times Chronic irritation of the pelvic peritoneum by the elevated incidence in first diploma relatives. All of the following characteristics: (1) apparently regular prenatal and perinatal improvement (2) apparently regular psychomotor improvement via the primary 5 months after start (three) regular head circumference at delivery B. After making certain that the topic has understood the knowledge, the physician should then acquire the topic's freely-given informed consent, preferably in writing <a href=https://www.lifemedical.us/clinical-approach/article682/> fungus gnats get rid buy cheap fluconazole 150mg</a>. The health professional should think about reporting directly to the driving force licensing authority in situations where the patient is both: пїЅ unable to understand the influence of their condition пїЅ unable to take notice of the health professionalпїЅs recommendations because of cognitive impairment, or пїЅ continues driving regardless of applicable advice and is more likely to endanger the general public. Presently, market information is usually conveyed by way of agro-dealers and commodity assemblers who are often selective in their messages provided. The major significance of this illness is the cardiac involvement which may ultimately result in extreme coronary heart valve injury <a href=https://www.lifemedical.us/clinical-approach/article679/> hypertension or high blood pressure telmisartan 80mg on line</a>. Palmar Suggested by: related evidence of liver cirrhosis, pregnancy, erythema and polycythaemia. Embryos for transfer to the momпїЅs uterus could be selected from the chromosomally normal embryos. Finally, reviewed articles usually define and measure violence in different methods, and we goal to make our discussion in keeping with authentic research, each time potential <a href=https://www.lifemedical.us/clinical-approach/article684/> medicine 3605 buy generic domperidone 10mg line</a>.","date":"2020-09-16T11:19:33.689Z"}